{"home":"главная страница","search":"поиск","categories":"по категориям","author_quote_quote":"%s цитата: %s","more_info_link":"(%sдополнительная информация%s)","anonymous":"автор неизвестен","contributed_by_s":"кто добавил %s","none_found_try_again":"Извините! Ничего не найдено. Попробовать еще раз?","author":"автор","authors":"авторы","contributor":"контрибьютор","contributors":"контрибьюторы","top_s":"самые популярные %s","new":"новое","musicthoughts":"Высказывания о музыке","musicthoughts_slogan":"тихое местечко, где можно подумать о музыке","random_thought":"случайное высказывание","list_thoughts":"список высказываний","newest_thoughts":"самые последние высказывания","search_intro":"поиск любой темы, инструмента, музыканта, чего угодно...","from":"откуда","submit":"отправить","about1":"Меня зовут Дерек Сайверс.","about2":"Я был музыкантом с 1984 года, а профессиональным музыкантом в течение 13 лет.","about3":"В 1998 г. я создал cdbaby.com и hostbaby.com","about4":"В 1999 г. я создал musicthoughts.com, так как мне очень нравилось, как мысли других музыкантов о создании музыки вдохновляли меня, когда я создавал свою музыку.","about5":"Также вы можете присоединиться к %sсписок почтовой рассылки musicthoughts%s, чтобы пообщаться с другими музыкантами.","about6":"musicthoughts.com представляет собой совершенно бесплатный некоммерческий сайт, только для вашего вдохновения.","about7":"Если у вас имеется идея, что бы это могло быть еще, %sсвяжитесь со мной%s.","about8":"Все мои новые проекты находятся на %ssivers.org%s","about":"обо"}
